testcontainers/neo4j/__init__.py
tests/test_neo4j.py
testcontainers_neo4j-0.0.1rc1.dist-info/METADATA
testcontainers_neo4j-0.0.1rc1.dist-info/WHEEL
testcontainers_neo4j-0.0.1rc1.dist-info/top_level.txt
testcontainers_neo4j-0.0.1rc1.dist-info/RECORD
