Metadata-Version: 2.1
Name: testcontainers-neo4j
Version: 0.0.1rc1
Summary: Neo4j component of testcontainers-python.
Home-page: https://github.com/testcontainers/testcontainers-python
Requires-Python: >=3.7
Requires-Dist: testcontainers-core
Requires-Dist: neo4j
